stocktickers/__init__.py
stocktickers/canada.py
stocktickers/china.py
stocktickers/france.py
stocktickers/germany.py
stocktickers/hongkong.py
stocktickers/italy.py
stocktickers/japan.py
stocktickers/nasdaq.py
stocktickers/nyse.py
stocktickers/uk.py
stocktickers-0.0.18.dist-info/licenses/LICENSE
stocktickers-0.0.18.dist-info/METADATA
stocktickers-0.0.18.dist-info/WHEEL
stocktickers-0.0.18.dist-info/top_level.txt
stocktickers-0.0.18.dist-info/RECORD
