Metadata-Version: 2.4
Name: stocktickers
Version: 0.0.18
Summary: List of stock tickers of specific countries gathered in one simple package.
Author-email: Taha Shieenavaz <tahashieenavaz@gmail.com>
License: MIT License
Project-URL: Homepage, https://github.com/tahashieenavaz/stocktickers
Project-URL: Repository, https://github.com/tahashieenavaz/stocktickers
Project-URL: Documentation, https://github.com/tahashieenavaz/stocktickers#readme
Keywords: finance,python finance
Classifier: Programming Language :: Python :: 3
Classifier: License :: OSI Approved :: MIT License
Classifier: Operating System :: OS Independent
Classifier: Development Status :: 4 - Beta
Classifier: Intended Audience :: Developers
Classifier: Topic :: Software Development :: Libraries :: Python Modules
Requires-Python: >=3.9
License-File: LICENSE
Requires-Dist: numpy
Requires-Dist: pandas
Dynamic: license-file
